q.py
q_bot-1.4.0.dist-info/METADATA
q_bot-1.4.0.dist-info/WHEEL
q_bot-1.4.0.dist-info/entry_points.txt
q_bot-1.4.0.dist-info/top_level.txt
q_bot-1.4.0.dist-info/RECORD
