Metadata-Version: 2.4
Name: q-bot
Version: 1.4.0
Summary: An LLM-powered programming copilot from the comfort of your command line
Author-email: Tushar Khan <tushar.54k@gmail.com>
License-Expression: MIT
Project-URL: Repository, https://github.com/tk755/q
Requires-Python: >=3.8
Requires-Dist: colorama==0.4.6
Requires-Dist: openai==1.82.0
Requires-Dist: pyperclip==1.9.0
Requires-Dist: termcolor==2.5.0
